CheeseAPI_Websocket/__init__.py
CheeseAPI_Websocket/handle.py
CheeseAPI_Websocket/websocket.py
cheeseapi_websocket-1.1.1.dist-info/METADATA
cheeseapi_websocket-1.1.1.dist-info/WHEEL
cheeseapi_websocket-1.1.1.dist-info/licenses/LICENSE
cheeseapi_websocket-1.1.1.dist-info/RECORD
