Metadata-Version: 2.4
Name: CheeseAPI_Websocket
Version: 1.1.1
Summary: 一款基于CheeseAPI的升级款Websocket插件。
Project-URL: Source, https://github.com/CheeseUnknown/CheeseAPI_Websocket
Author-email: Cheese Unknown <cheese@cheese.ren>
License-File: LICENSE
Keywords: CheeseAPI,websocket
Requires-Dist: cheeseapi==1.7.*
Requires-Dist: redis
